odoo/addons/stock_request_sequence_option/README.rst
odoo/addons/stock_request_sequence_option/__init__.py
odoo/addons/stock_request_sequence_option/__manifest__.py
odoo/addons/stock_request_sequence_option/data/stock_request_sequence_option.xml
odoo/addons/stock_request_sequence_option/demo/stock_request_demo_options.xml
odoo/addons/stock_request_sequence_option/i18n/it.po
odoo/addons/stock_request_sequence_option/i18n/stock_request_sequence_option.pot
odoo/addons/stock_request_sequence_option/models/__init__.py
odoo/addons/stock_request_sequence_option/models/sequence_option.py
odoo/addons/stock_request_sequence_option/models/stock_request.py
odoo/addons/stock_request_sequence_option/models/stock_request_order.py
odoo/addons/stock_request_sequence_option/readme/CONTRIBUTORS.rst
odoo/addons/stock_request_sequence_option/readme/DESCRIPTION.rst
odoo/addons/stock_request_sequence_option/static/description/icon.png
odoo/addons/stock_request_sequence_option/static/description/index.html
odoo/addons/stock_request_sequence_option/tests/__init__.py
odoo/addons/stock_request_sequence_option/tests/test_stock_request_sequence_option.py
odoo14_addon_stock_request_sequence_option-14.0.1.0.1.dev5.dist-info/METADATA
odoo14_addon_stock_request_sequence_option-14.0.1.0.1.dev5.dist-info/WHEEL
odoo14_addon_stock_request_sequence_option-14.0.1.0.1.dev5.dist-info/top_level.txt
odoo14_addon_stock_request_sequence_option-14.0.1.0.1.dev5.dist-info/RECORD
