Metadata-Version: 2.1
Name: odoo14-addon-stock_request_sequence_option
Version: 14.0.1.0.1.dev5
Summary: Manage sequence options for stock request
Home-page: https://github.com/OCA/stock-logistics-warehouse
Author: Ecosoft, Odoo Community Association (OCA)
Author-email: support@odoo-community.org
License: AGPL-3
Classifier: Programming Language :: Python
Classifier: Framework :: Odoo
Classifier: Framework :: Odoo :: 14.0
Classifier: License :: OSI Approved :: GNU Affero General Public License v3
Classifier: Development Status :: 3 - Alpha
Requires-Python: >=3.6
Requires-Dist: odoo14-addon-base-sequence-option
Requires-Dist: odoo14-addon-stock-request
Requires-Dist: odoo<14.1dev,>=14.0a
